setup.py
alifunc_http/__init__.py
alifunc_http/client.py
alifunc_http.egg-info/PKG-INFO
alifunc_http.egg-info/SOURCES.txt
alifunc_http.egg-info/dependency_links.txt
alifunc_http.egg-info/requires.txt
alifunc_http.egg-info/top_level.txt
alifunc_http.egg-info/zip-safe