Metadata-Version: 2.1
Name: alifunc-http
Version: 0.0.2
Summary: Ali serverless http client
Home-page: UNKNOWN
Author: cbnSpider
License: UNKNOWN
Platform: UNKNOWN
Classifier: Programming Language :: Python
Classifier: Programming Language :: Python :: 3
Classifier: Programming Language :: Python :: 3.5
Classifier: Programming Language :: Python :: 3.6
Classifier: Programming Language :: Python :: 3.7
